wandatoolbox/__init__.py
wandatoolbox/util.py
wandatoolbox/wanda_plot.py
wandatoolbox-0.1.0.dist-info/LICENSE
wandatoolbox-0.1.0.dist-info/METADATA
wandatoolbox-0.1.0.dist-info/WHEEL
wandatoolbox-0.1.0.dist-info/top_level.txt
wandatoolbox-0.1.0.dist-info/RECORD
