Metadata-Version: 2.1
Name: wandatoolbox
Version: 0.1.0
Summary: Python toolbox for Wanda
Home-page: https://github.com/MichielTukker/WandaToolbox
Author: Michiel Tukker
Author-email: Michiel.Tukker@deltares.nl
License: UNKNOWN
Platform: UNKNOWN
Classifier: Programming Language :: Python :: 3
Classifier: Programming Language :: Python :: 3.6
Classifier: Programming Language :: Python :: 3.7
Classifier: Programming Language :: Python :: 3.8
Classifier: License :: OSI Approved :: GNU General Public License v3 (GPLv3)
Classifier: Operating System :: OS Independent
Classifier: Development Status :: 3 - Alpha
Classifier: Intended Audience :: Developers
Classifier: Intended Audience :: Science/Research
Classifier: Intended Audience :: Information Technology
Classifier: Topic :: Scientific/Engineering
Classifier: Topic :: Scientific/Engineering :: Mathematics
Classifier: Topic :: Scientific/Engineering :: Physics
Requires-Python: >=3.6
Requires-Dist: pywanda (>=0.4.1)
Requires-Dist: matplotlib (>=3.1.3)
Requires-Dist: pandas (>=1.0.1)
Requires-Dist: numpy (>=1.18.1)
Provides-Extra: dev
Requires-Dist: pytest (==5.3.5) ; extra == 'dev'
Requires-Dist: bump2version (==1.0.0) ; extra == 'dev'
